[{"name_kr":"김성곤","name_cn":"金星坤","party":"새정치민주연합","district":null,"id":327},{"name_kr":"민홍철","name_cn":"閔洪喆","party":"새정치민주연합","district":null,"id":396},{"name_kr":"박민수","name_cn":"朴敏秀","party":"새정치민주연합","district":null,"id":298},{"name_kr":"박병석","name_cn":"朴炳錫","party":"새정치민주연합","district":null,"id":447},{"name_kr":"신경민","name_cn":"辛京珉","party":"새정치민주연합","district":null,"id":346},{"name_kr":"원혜영","name_cn":"元惠榮","party":"새정치민주연합","district":null,"id":309},{"name_kr":"윤호중","name_cn":"尹昊重","party":"새정치민주연합","district":null,"id":356},{"name_kr":"이상민","name_cn":"李相珉","party":"새정치민주연합","district":null,"id":381},{"name_kr":"추미애","name_cn":"秋美愛","party":"새정치민주연합","district":null,"id":351},{"name_kr":"홍종학","name_cn":"洪鍾學","party":"새정치민주연합","district":null,"id":424}]