[{"name_kr":"홍영표","name_cn":"","party":"","district":null,"id":587,"c":5},{"name_kr":"오영식","name_cn":"","party":"","district":null,"id":520,"c":3},{"name_kr":"최민희","name_cn":"","party":"","district":null,"id":619,"c":3},{"name_kr":"박주선","name_cn":"","party":"","district":null,"id":502,"c":2},{"name_kr":"이개호","name_cn":"","party":"","district":null,"id":513,"c":2},{"name_kr":"민홍철","name_cn":"","party":"","district":null,"id":565,"c":2},{"name_kr":"조정식","name_cn":"","party":"","district":null,"id":522,"c":2},{"name_kr":"노영민","name_cn":"","party":"","district":null,"id":542,"c":2},{"name_kr":"박완주","name_cn":"","party":"","district":null,"id":546,"c":2},{"name_kr":"김승남","name_cn":"","party":"","district":null,"id":582,"c":2},{"name_kr":"이원욱","name_cn":"","party":"","district":null,"id":549,"c":2}]