[{"name_kr":"김승남","name_cn":"","party":"","district":null,"id":566},{"name_kr":"김현","name_cn":"","party":"","district":null,"id":619},{"name_kr":"박완주","name_cn":"","party":"","district":null,"id":533},{"name_kr":"박주선","name_cn":"","party":"","district":null,"id":495},{"name_kr":"박홍근","name_cn":"","party":"","district":null,"id":598},{"name_kr":"윤관석","name_cn":"","party":"","district":null,"id":514},{"name_kr":"인재근","name_cn":"","party":"","district":null,"id":588},{"name_kr":"임수경","name_cn":"","party":"","district":null,"id":569},{"name_kr":"전순옥","name_cn":"","party":"","district":null,"id":589},{"name_kr":"홍익표","name_cn":"","party":"","district":null,"id":620}]