[
    {
        "name": "홍지만",
        "cname": "",
        "party": "",
        "id": 523,
        "c": 1
    },
    {
        "name": "박명재",
        "cname": "",
        "party": "",
        "id": 546,
        "c": 1
    },
    {
        "name": "양창영",
        "cname": "",
        "party": "",
        "id": 443,
        "c": 1
    },
    {
        "name": "김도읍",
        "cname": "",
        "party": "",
        "id": 586,
        "c": 1
    },
    {
        "name": "이정현",
        "cname": "",
        "party": "",
        "id": 471,
        "c": 1
    },
    {
        "name": "이노근",
        "cname": "",
        "party": "",
        "id": 526,
        "c": 1
    },
    {
        "name": "이찬열",
        "cname": "",
        "party": "",
        "id": 334,
        "c": 1
    },
    {
        "name": "이강후",
        "cname": "",
        "party": "",
        "id": 548,
        "c": 1
    },
    {
        "name": "이우현",
        "cname": "",
        "party": "",
        "id": 468,
        "c": 1
    },
    {
        "name": "정두언",
        "cname": "",
        "party": "",
        "id": 587,
        "c": 1
    }
]