[{"id":3934,"link_id":"PRC_A1M3L0P4C2U9A1J5X0G6E5O7F0L8F8","bill_id":"1904708","title":"성매매방지 및 피해자보호 등에 관한 법률 일부개정법률안","proposed_date":"2013-04-29","decision_date":"2014-02-28","status":"처리","status_detail":"대안반영폐기","actor_count":17},{"id":6944,"link_id":"PRC_T1L3I0F4F1A8N1H8I1H3Q2O9S1B7M3","bill_id":"1904590","title":"농어업재해대책법 일부개정법률안","proposed_date":"2013-04-18","decision_date":"2014-02-28","status":"처리","status_detail":"대안반영폐기","actor_count":28},{"id":8031,"link_id":"PRC_W1G3A0E4L1G8Z1G1Z1B8U0N3X8X7G7","bill_id":"1904568","title":"낙후심화지역 지원에 관한 특별법안","proposed_date":"2013-04-18","decision_date":"2014-04-29","status":"처리","status_detail":"대안반영폐기","actor_count":10},{"id":17221,"link_id":"PRC_J1W3R0P4N1E6F1S6A4T5H1F3D1W2P9","bill_id":"1904535","title":"선행교육 규제에 관한 특별법안","proposed_date":"2013-04-16","decision_date":"2014-02-20","status":"처리","status_detail":"대안반영폐기","actor_count":29},{"id":13967,"link_id":"PRC_N1I3H0C4B1D2O1S4L4C3Z3J4Z2S6W1","bill_id":"1904501","title":"개인정보 보호법 일부개정법률안","proposed_date":"2013-04-12","decision_date":"2016-03-02","status":"처리","status_detail":"대안반영폐기","actor_count":10},{"id":5044,"link_id":"PRC_T1N3H0T4S1N0O1I7I4A7E3Z7X9F6W1","bill_id":"1904477","title":"결혼중개업의 관리에 관한 법률 일부개정법률안","proposed_date":"2013-04-10","decision_date":"2013-07-02","status":"처리","status_detail":"공포","actor_count":10},{"id":784,"link_id":"PRC_C1M3B0P4L0E9E1B3S5F0E4K1L6I7W6","bill_id":"1904447","title":"원양산업발전법 일부개정법률안","proposed_date":"2013-04-09","decision_date":"2013-07-02","status":"처리","status_detail":"대안반영폐기","actor_count":12},{"id":2862,"link_id":"PRC_L1N3J0S4K0D8W1W7I1K2W4S0D3T7J3","bill_id":"1904436","title":"국세기본법 일부개정법률안","proposed_date":"2013-04-08","decision_date":"2015-12-14","status":"처리","status_detail":"폐기","actor_count":14},{"id":15978,"link_id":"PRC_T1H3Z0B4J0J8V1Y8D2M0M2X8Q0Q8Y4","bill_id":"1904442","title":"화학물질의 등록 및 평가 등에 관한 법률안","proposed_date":"2013-04-08","decision_date":"2013-04-30","status":"처리","status_detail":"대안반영폐기","actor_count":10},{"id":7574,"link_id":"PRC_C1T3U0A4P0G5I1E5A5C0E5U8S3P8X5","bill_id":"1904416","title":"개발제한구역의 지정 및 관리에 관한 특별조치법 일부개정법률안","proposed_date":"2013-04-05","decision_date":"2013-05-27","status":"처리","status_detail":"철회","actor_count":11},{"id":7574,"link_id":"PRC_C1T3U0A4P0G5I1E5A5C0E5U8S3P8X5","bill_id":"1904416","title":"개발제한구역의 지정 및 관리에 관한 특별조치법 일부개정법률안","proposed_date":"2013-04-05","decision_date":"2013-05-27","status":"처리","status_detail":"철회","actor_count":11},{"id":8292,"link_id":"PRC_M1I3R0U4F0P4F1U5O1K9C2K2D4Y6F4","bill_id":"1904387","title":"새만금사업 추진 및 지원에 관한 특별법 일부개정법률안","proposed_date":"2013-04-04","decision_date":"2013-06-27","status":"처리","status_detail":"공포","actor_count":11},{"id":13697,"link_id":"PRC_Q1F3H0N3H2J9H1L4I4M1U2E8F7K4E6","bill_id":"1904331","title":"소방시설 설치·유지 및 안전관리에 관한 법률 일부개정법률안","proposed_date":"2013-03-29","decision_date":"2013-12-19","status":"처리","status_detail":"대안반영폐기","actor_count":15},{"id":17841,"link_id":"PRC_B1L3I0J3A2B6R1P7D2N5Z3Y0Y5N4X0","bill_id":"1904282","title":"개발이익환수에 관한 법률 일부개정법률안","proposed_date":"2013-03-26","decision_date":"2015-07-24","status":"처리","status_detail":"대안반영폐기","actor_count":10},{"id":11890,"link_id":"PRC_P1H3C0M3W2R6A1D4A3T7I2D2Y7F1J4","bill_id":"1904270","title":"범죄피해자보호기금법 일부개정법률안","proposed_date":"2013-03-26","decision_date":"2014-09-30","status":"처리","status_detail":"대안반영폐기","actor_count":14},{"id":13584,"link_id":"PRC_X1X3B0J3M2E5W1A5T5V1Z3D2N3N3B0","bill_id":"1904248","title":"노인복지법 일부개정법률안","proposed_date":"2013-03-25","decision_date":"2014-12-29","status":"처리","status_detail":"대안반영폐기","actor_count":12},{"id":15165,"link_id":"PRC_J1V3G0M3K2B5X1L7S4A6C3V5F3G3J3","bill_id":"1904252","title":"가습기 살균제 피해자 구제를 위한 결의안","proposed_date":"2013-03-25","decision_date":"2013-04-29","status":"처리","status_detail":"의결","actor_count":26},{"id":5540,"link_id":"PRC_B1W3E0X3I2K2J1Z0O0W9C2N2A4W3T0","bill_id":"1904208","title":"독립유공자예우에 관한 법률 일부개정법률안","proposed_date":"2013-03-22","decision_date":"2014-05-02","status":"처리","status_detail":"대안반영폐기","actor_count":16},{"id":13789,"link_id":"PRC_E1I3B0W3R2F1H1H1K5C3G5G6X8L8B1","bill_id":"1904187","title":"도로교통법 일부개정법률안","proposed_date":"2013-03-21","decision_date":"2013-12-31","status":"처리","status_detail":"대안반영폐기","actor_count":19},{"id":690,"link_id":"PRC_O1S3H0D3P2X1G1I0T3A8W5P9F1Y0N7","bill_id":"1904183","title":"청원경찰법 일부개정법률안","proposed_date":"2013-03-21","decision_date":"2014-12-09","status":"처리","status_detail":"대안반영폐기","actor_count":10},{"id":1636,"link_id":"PRC_D1S3J0X3H2Q0O1L7G5C9Q4L5Q2B0M7","bill_id":"1904177","title":"학교밖 학업중단 청소년 지원에 관한 법률안","proposed_date":"2013-03-20","decision_date":"2014-05-02","status":"처리","status_detail":"대안반영폐기","actor_count":10},{"id":12175,"link_id":"PRC_M1C3J0Y3Z1Q9Q1O6B0Z8H1Y8J1B5A3","bill_id":"1904130","title":"공직자윤리법 일부개정법률안","proposed_date":"2013-03-19","decision_date":"2014-12-09","status":"처리","status_detail":"대안반영폐기","actor_count":12},{"id":17719,"link_id":"PRC_J1X3V0W3O1T8Y1I3Z3Q1R4C7W9Q8L5","bill_id":"1904107","title":"정신보건법 일부개정법률안","proposed_date":"2013-03-18","decision_date":"2014-12-29","status":"처리","status_detail":"대안반영폐기","actor_count":15},{"id":11682,"link_id":"PRC_K1S3F0R3A1K5P1Z4X4L6N2F1U7W0U0","bill_id":"1904086","title":"소득세법 일부개정법률안","proposed_date":"2013-03-15","decision_date":"2015-12-14","status":"처리","status_detail":"폐기","actor_count":14},{"id":6969,"link_id":"PRC_Y1Y3Y0Z3X0A8S1P4P1Q2Y1Q7G7T4E5","bill_id":"1904001","title":"가정폭력방지 및 피해자보호 등에 관한 법률 일부개정법률안","proposed_date":"2013-03-08","decision_date":"2014-01-03","status":"처리","status_detail":"폐기","actor_count":13},{"id":4893,"link_id":"PRC_O1V3X0A3H0O5E1M4Z1S9M3L3F5W1V3","bill_id":"1903960","title":"전기사업법 일부개정법률안","proposed_date":"2013-03-05","decision_date":"2013-06-25","status":"처리","status_detail":"대안반영폐기","actor_count":10},{"id":15359,"link_id":"PRC_Y1Z3B0B2F2M8O1N5M3R6T0M0Z6U4N1","bill_id":"1903913","title":"소음·진동관리법 일부개정법률안","proposed_date":"2013-02-28","decision_date":"2013-07-02","status":"처리","status_detail":"대안반영폐기","actor_count":16},{"id":9332,"link_id":"PRC_R1B3Q0W2Y2C7P1E7B5J6W2Z7P2J5Z3","bill_id":"1903897","title":"여성발전기본법 일부개정법률안","proposed_date":"2013-02-27","decision_date":"2013-12-10","status":"처리","status_detail":"대안반영폐기","actor_count":10},{"id":16071,"link_id":"PRC_X1C3S0G2B2M6E1M5X2D2J4Z4L1R4L2","bill_id":"1903877","title":"소음·진동관리법 일부개정법률안","proposed_date":"2013-02-26","decision_date":"2013-02-28","status":"처리","status_detail":"철회","actor_count":17},{"id":16071,"link_id":"PRC_X1C3S0G2B2M6E1M5X2D2J4Z4L1R4L2","bill_id":"1903877","title":"소음·진동관리법 일부개정법률안","proposed_date":"2013-02-26","decision_date":"2013-02-28","status":"처리","status_detail":"철회","actor_count":17},{"id":10563,"link_id":"PRC_X1K3G0D2J2E2K1M5R2O7M3M3A2N8Z7","bill_id":"1903839","title":"소득세법 일부개정법률안","proposed_date":"2013-02-22","decision_date":"2013-03-15","status":"처리","status_detail":"철회","actor_count":14},{"id":10563,"link_id":"PRC_X1K3G0D2J2E2K1M5R2O7M3M3A2N8Z7","bill_id":"1903839","title":"소득세법 일부개정법률안","proposed_date":"2013-02-22","decision_date":"2013-03-15","status":"처리","status_detail":"철회","actor_count":14},{"id":17050,"link_id":"PRC_G1S3F0L2S1T4Y1R1C5X2N3D1H8P1V1","bill_id":"1903717","title":"국립묘지의 설치 및 운영에 관한 법률 일부개정법률안","proposed_date":"2013-02-14","decision_date":"2013-06-25","status":"처리","status_detail":"대안반영폐기","actor_count":13},{"id":16379,"link_id":"PRC_N1T3G0D2R1A4J1O2Z1Z2T2C3Q0B6M6","bill_id":"1903721","title":"공무원연금법 일부개정법률안","proposed_date":"2013-02-14","decision_date":"2013-06-25","status":"처리","status_detail":"대안반영폐기","actor_count":13},{"id":12223,"link_id":"PRC_F1T3K0S2G0Y7S1B4D1W8D5K4B5I8A4","bill_id":"1903654","title":"할부거래에 관한 법률 일부개정법률안","proposed_date":"2013-02-07","decision_date":"2015-07-06","status":"처리","status_detail":"대안반영폐기","actor_count":15},{"id":12891,"link_id":"PRC_W1S3N0K2T0W6I1W5Z2P4C3F6U9O9K2","bill_id":"1903645","title":"전기사업법 일부개정법률안","proposed_date":"2013-02-06","decision_date":"2013-06-25","status":"처리","status_detail":"대안반영폐기","actor_count":13},{"id":9574,"link_id":"PRC_Y1U3I0Q2I0B5J1L8S2N1C1X1U9Z0J2","bill_id":"1903637","title":"정부조직법 일부개정법률안","proposed_date":"2013-02-05","decision_date":"2015-04-16","status":"처리","status_detail":"폐기","actor_count":22},{"id":2813,"link_id":"PRC_V1B3N0T2E0T5Y1V8C2G7M4K2X3H5M0","bill_id":"1903638","title":"방송통신위원회의 설치 및 운영에 관한 법률 일부개정법률안","proposed_date":"2013-02-05","decision_date":"2013-03-22","status":"처리","status_detail":"대안반영폐기","actor_count":22},{"id":7750,"link_id":"PRC_R1G3C0U1U2D8P1F7N0P6T4D2J2T9B8","bill_id":"1903441","title":"전기통신사업법 일부개정법률안","proposed_date":"2013-01-28","decision_date":"2014-09-30","status":"처리","status_detail":"대안반영폐기","actor_count":10},{"id":3624,"link_id":"PRC_Z1O3W0G1L2M8Q1T7O2H0Q2R1F6V0U4","bill_id":"1903442","title":"대부업 등의 등록 및 금융이용자 보호에 관한 법률 일부개정법률안","proposed_date":"2013-01-28","decision_date":"2015-07-06","status":"처리","status_detail":"대안반영폐기","actor_count":26},{"id":19331,"link_id":"PRC_D1J3P0U1T2H8P1T6R1R8W3W8V9R7R1","bill_id":"1903439","title":"하도급거래 공정화에 관한 법률 일부개정법률안","proposed_date":"2013-01-28","decision_date":"2013-06-25","status":"처리","status_detail":"대안반영폐기","actor_count":15},{"id":3996,"link_id":"PRC_N1C3Q0O1K2U1D1W6Z0G4Y3V5K0X7E0","bill_id":"1903374","title":"전기통신사업법 일부개정법률안","proposed_date":"2013-01-21","decision_date":"2014-12-29","status":"처리","status_detail":"대안반영폐기","actor_count":13},{"id":13424,"link_id":"PRC_B1N3S0P1Z1Y4Y1P5P5O5F2U0Y0X5P8","bill_id":"1903313","title":"예술인 복지법 일부개정법률안","proposed_date":"2013-01-14","decision_date":"2013-12-10","status":"처리","status_detail":"대안반영폐기","actor_count":27},{"id":13397,"link_id":"PRC_A1S3Y0M1C0J9R1J3N2F9N5G8B3F1R2","bill_id":"1903267","title":"출판문화산업 진흥법 일부개정법률안","proposed_date":"2013-01-09","decision_date":"2014-04-29","status":"처리","status_detail":"공포","actor_count":16},{"id":2747,"link_id":"PRC_A1V3C0V1U0M3O1V7U2Y3T5H1Y6L8E7","bill_id":"1903240","title":"공예문화산업 진흥법안","proposed_date":"2013-01-03","decision_date":"2015-04-30","status":"처리","status_detail":"공포","actor_count":22},{"id":15686,"link_id":"PRC_F1A3B0P1V0Q3L1R5C2K3K4Y1G6Z7G8","bill_id":"1903236","title":"태권도 진흥 및 태권도공원 조성 등에 관한 법률 일부개정법률안","proposed_date":"2013-01-03","decision_date":"2014-02-20","status":"처리","status_detail":"공포","actor_count":12},{"id":16966,"link_id":"PRC_V1O2Z1R2N3M1F1Z6B2Q2Z4E3B8U4I5","bill_id":"1903171","title":"전기통신사업법 일부개정법률안","proposed_date":"2012-12-31","decision_date":"2013-01-17","status":"처리","status_detail":"철회","actor_count":11},{"id":16346,"link_id":"PRC_U1J2B1Z2R3N1H1B0S2G2T5J2C3Q3N3","bill_id":"1903163","title":"변호사법 일부개정법률안","proposed_date":"2012-12-31","decision_date":"2014-04-29","status":"처리","status_detail":"대안반영폐기","actor_count":10},{"id":16966,"link_id":"PRC_V1O2Z1R2N3M1F1Z6B2Q2Z4E3B8U4I5","bill_id":"1903171","title":"전기통신사업법 일부개정법률안","proposed_date":"2012-12-31","decision_date":"2013-01-17","status":"처리","status_detail":"철회","actor_count":11},{"id":18305,"link_id":"PRC_Y1A2M1O2B1D4Q1C4D5U1K3R6P9Y4B4","bill_id":"1903091","title":"국립묘지의 설치 및 운영에 관한 법률 일부개정법률안","proposed_date":"2012-12-14","decision_date":"2013-06-25","status":"처리","status_detail":"대안반영폐기","actor_count":12},{"id":14106,"link_id":"PRC_P1S2S1M2W1X0J1Z1A1P8F2R3C0C8Q2","bill_id":"1903062","title":"공공기관의 정보공개에 관한 법률 일부개정법률안","proposed_date":"2012-12-10","decision_date":"2013-06-27","status":"처리","status_detail":"대안반영폐기","actor_count":17},{"id":3619,"link_id":"PRC_S1J2T1Y2X1F0M1T5Q5P3I2Q2J4M5I3","bill_id":"1903064","title":"신에너지 및 재생에너지 개발·이용·보급 촉진법 일부개정법률안","proposed_date":"2012-12-10","decision_date":"2013-06-25","status":"처리","status_detail":"대안반영폐기","actor_count":12},{"id":8127,"link_id":"PRC_R1N2H1D2G0R5K1J7G2Z3W5K7U4J6A6","bill_id":"1902934","title":"국세기본법 일부개정법률안","proposed_date":"2012-12-05","decision_date":"2015-12-14","status":"처리","status_detail":"폐기","actor_count":12},{"id":410,"link_id":"PRC_M1A2O1M1B2H0O1U5O0W3N5R3L7Z1Q5","bill_id":"1902677","title":"먹는물관리법 일부개정법률안","proposed_date":"2012-11-20","decision_date":"2013-12-26","status":"처리","status_detail":"대안반영폐기","actor_count":10},{"id":11231,"link_id":"PRC_Z1B2B1R1I1Z9P1N7B1U7C4X2U7A8S4","bill_id":"1902666","title":"민법 일부개정법률안","proposed_date":"2012-11-19","decision_date":"2013-03-05","status":"처리","status_detail":"공포","actor_count":10},{"id":18710,"link_id":"PRC_W1I2G1D1S1P9B1T7N1V9A4E3F2H5N4","bill_id":"1902667","title":"유실물법 일부개정법률안","proposed_date":"2012-11-19","decision_date":"2013-12-19","status":"처리","status_detail":"공포","actor_count":10},{"id":17633,"link_id":"PRC_L1Q2Q1V1U1V9V1D3O5E4A2L1Y1G2Y6","bill_id":"1902643","title":"한부모가족지원법 일부개정법률안","proposed_date":"2012-11-19","decision_date":"2013-05-02","status":"처리","status_detail":"폐기","actor_count":15},{"id":6435,"link_id":"PRC_I1T2D1X1O1B6L1K1H2A9K0H5J1J7C3","bill_id":"1902616","title":"부정경쟁방지 및 영업비밀보호에 관한 법률 일부개정법률안","proposed_date":"2012-11-16","decision_date":"2013-06-25","status":"처리","status_detail":"대안반영폐기","actor_count":10},{"id":5268,"link_id":"PRC_K1U2K1E1J1D5J1Q7M0Z3U3X3Z7B4P5","bill_id":"1902604","title":"이자제한법 일부개정법률안","proposed_date":"2012-11-15","decision_date":"2013-12-31","status":"처리","status_detail":"공포","actor_count":23},{"id":15464,"link_id":"PRC_G1I2R1K1B1H5J1K7X4G2V3N5N1L7Y9","bill_id":"1902608","title":"부패재산의 몰수 및 회복에 관한 특례법 일부개정법률안","proposed_date":"2012-11-15","decision_date":"2013-06-27","status":"처리","status_detail":"대안반영폐기","actor_count":11},{"id":9405,"link_id":"PRC_J1H2T1V1T1X5K1D7I2G7O3F4H8P1L3","bill_id":"1902606","title":"범죄수익은닉의 규제 및 처벌 등에 관한 법률 일부개정법률안","proposed_date":"2012-11-15","decision_date":"2013-06-27","status":"처리","status_detail":"대안반영폐기","actor_count":11},{"id":11855,"link_id":"PRC_U1C2R1J1L1F5V1S7Z5W1H0C3T4I6T2","bill_id":"1902610","title":"공무원범죄에 관한 몰수 특례법 일부개정법률안","proposed_date":"2012-11-15","decision_date":"2013-06-27","status":"처리","status_detail":"대안반영폐기","actor_count":11},{"id":744,"link_id":"PRC_C1S2A1W1W1N5N1B7G0W1W0O1K0K5B6","bill_id":"1902611","title":"채권의 공정한 추심에 관한 법률 일부개정법률안","proposed_date":"2012-11-15","decision_date":"2013-12-31","status":"처리","status_detail":"대안반영폐기","actor_count":22},{"id":17872,"link_id":"PRC_L1C2U1R1Z1T5C1N7L2W7G4D3X1S9U9","bill_id":"1902607","title":"형법 일부개정법률안","proposed_date":"2012-11-15","decision_date":"2013-06-27","status":"처리","status_detail":"대안반영폐기","actor_count":11},{"id":15531,"link_id":"PRC_N1D2O1C1U1Q5C1Z6V5R6U5Q7E0J9O7","bill_id":"1902602","title":"대부업 등의 등록 및 금융이용자 보호에 관한 법률 일부개정법률안","proposed_date":"2012-11-15","decision_date":"2013-12-26","status":"처리","status_detail":"대안반영폐기","actor_count":23},{"id":16865,"link_id":"PRC_V1S2T1A1U1B4N1H5B4W2T5I6V3O4Z8","bill_id":"1902575","title":"아동·청소년의 성보호에 관한 법률 일부개정법률안","proposed_date":"2012-11-14","decision_date":"2012-11-22","status":"처리","status_detail":"대안반영폐기","actor_count":10},{"id":12761,"link_id":"PRC_T1D2C1S1Q0B5I1E7V4K7L4C2K4G6X6","bill_id":"1902437","title":"새만금사업 추진 및 지원에 관한 특별법안","proposed_date":"2012-11-05","decision_date":"2012-11-22","status":"처리","status_detail":"공포","actor_count":172},{"id":9603,"link_id":"PRC_P1S2W1A1R0M2X1Z5Z4X2H3O4K5P2C7","bill_id":"1902393","title":"원자력안전법 일부개정법률안","proposed_date":"2012-11-02","decision_date":"2014-12-29","status":"처리","status_detail":"대안반영폐기","actor_count":10},{"id":9220,"link_id":"PRC_X1L2H1L1P0F1V1M1Y4U8R2H9T8S9N9","bill_id":"1902367","title":"집회 및 시위에 관한 법률 일부개정법률안","proposed_date":"2012-11-01","decision_date":"2015-12-31","status":"처리","status_detail":"대안반영폐기","actor_count":11}]