[{"id":17816,"link_id":"PRC_S1H5A0G9V1G4Z1U7P2G0R5K0C1G1D4","title":"식품·의약품분야 시험·검사 등에 관한 법률 일부개정법률안","proposed_date":"2015-09-14","decision_date":"0000-00-00","status":"계류","status_detail":"체계자구 심사","actor_count":11},{"id":15621,"link_id":"PRC_F1T5E0L8W2F4S1T7W1L9O2Z3R3S8T3","title":"선원법 일부개정법률안","proposed_date":"2015-08-24","decision_date":"0000-00-00","status":"계류","status_detail":"위원회 심사","actor_count":12},{"id":18717,"link_id":"PRC_W1N5E0T8Q2K1S1I8D2N0P0G6D9R7C2","title":"국민건강증진법 일부개정법률안","proposed_date":"2015-08-21","decision_date":"0000-00-00","status":"계류","status_detail":"위원회 심사","actor_count":11},{"id":9347,"link_id":"PRC_K1G5F0S8U2X1I1A8W0L3T4L8S1A3S2","title":"식품안전기본법 일부개정법률안","proposed_date":"2015-08-21","decision_date":"0000-00-00","status":"계류","status_detail":"위원회 심사","actor_count":12},{"id":3887,"link_id":"PRC_S1V5G0I8U2Y1K1U9H1E6I3D8M3E9K7","title":"소년법 일부개정법률안","proposed_date":"2015-08-21","decision_date":"0000-00-00","status":"계류","status_detail":"위원회 심사","actor_count":12},{"id":5506,"link_id":"PRC_Y1I5R0U8B2V1D1D8H2C2V3R3C1C4X4","title":"식품위생법 일부개정법률안","proposed_date":"2015-08-21","decision_date":"0000-00-00","status":"계류","status_detail":"위원회 심사","actor_count":12},{"id":17567,"link_id":"PRC_J1V5V0N8A2U1S1K8K0C9Y5C4K5F4R5","title":"축산물 위생관리법 일부개정법률안","proposed_date":"2015-08-21","decision_date":"0000-00-00","status":"계류","status_detail":"위원회 심사","actor_count":12},{"id":12866,"link_id":"PRC_R1Z5J0A4D2O0I2Z0L3T7U1U2G0R5P0","title":"의료법 일부개정법률안","proposed_date":"2015-04-20","decision_date":"0000-00-00","status":"계류","status_detail":"위원회 심사","actor_count":13},{"id":4836,"link_id":"PRC_D1P5Y0C2I2V7J1R7G3W9F3R3U9Z0B9","title":"담배사업법 일부개정법률안","proposed_date":"2015-02-27","decision_date":"0000-00-00","status":"계류","status_detail":"위원회 심사","actor_count":15},{"id":11540,"link_id":"PRC_H1W4C1S2G2Q2A1G7C4S4P3P5Z7B9U6","title":"영유아보육법 일부개정법률안","proposed_date":"2014-12-22","decision_date":"0000-00-00","status":"계류","status_detail":"위원회 심사","actor_count":10},{"id":6033,"link_id":"PRC_C1B4U1Q2G0W2F1J4E1N0S0A8H2K7D4","title":"암관리법 일부개정법률안","proposed_date":"2014-12-02","decision_date":"0000-00-00","status":"계류","status_detail":"위원회 심사","actor_count":10},{"id":7019,"link_id":"PRC_H1B4U1Q1E1N8K1N7Z4Z7R3S6R0A8Q8","title":"식품위생법 일부개정법률안","proposed_date":"2014-11-18","decision_date":"0000-00-00","status":"계류","status_detail":"위원회 심사","actor_count":11},{"id":3748,"link_id":"PRC_O1Z4S1V1Q1H8N1E8Z2Z2X3J0F8A9R4","title":"발전소주변지역 지원에 관한 법률 일부개정법률안","proposed_date":"2014-11-18","decision_date":"0000-00-00","status":"계류","status_detail":"위원회 심사","actor_count":10},{"id":6059,"link_id":"PRC_L1B4A1U0Y2O9Z1Q0L2N1E5B0G2N9R0","title":"형사소송법 일부개정법률안","proposed_date":"2014-10-29","decision_date":"0000-00-00","status":"계류","status_detail":"위원회 심사","actor_count":10}]