[{"name_kr":"강동원","name_cn":"姜東遠","party":"새정치민주연합","district":null,"id":329},{"name_kr":"김미희","name_cn":"金美希","party":"통합진보당","district":null,"id":314},{"name_kr":"김선동","name_cn":"金先東","party":"통합진보당","district":null,"id":315},{"name_kr":"김제남","name_cn":"金霽南","party":"정의당","district":"비례대표","id":51},{"name_kr":"노회찬","name_cn":"魯會燦","party":"정의당","district":null,"id":503},{"name_kr":"박원석","name_cn":"朴元錫","party":"정의당","district":"비례대표","id":104},{"name_kr":"심상정","name_cn":"沈相정","party":"정의당","district":null,"id":403},{"name_kr":"오병윤","name_cn":"吳秉潤","party":"통합진보당","district":null,"id":321},{"name_kr":"이상규","name_cn":"李相奎","party":"통합진보당","district":null,"id":322},{"name_kr":"정진후","name_cn":"鄭鎭珝","party":"정의당","district":"비례대표","id":249}]