[
    {
        "name": "유승희",
        "cname": "",
        "party": "",
        "id": 457,
        "c": 2
    },
    {
        "name": "김상희",
        "cname": "",
        "party": "",
        "id": 491,
        "c": 2
    },
    {
        "name": "이석현",
        "cname": "",
        "party": "",
        "id": 518,
        "c": 2
    },
    {
        "name": "김영록",
        "cname": "",
        "party": "",
        "id": 473,
        "c": 1
    },
    {
        "name": "유성엽",
        "cname": "",
        "party": "",
        "id": 333,
        "c": 1
    },
    {
        "name": "전정희",
        "cname": "",
        "party": "",
        "id": 514,
        "c": 1
    },
    {
        "name": "백재현",
        "cname": "",
        "party": "",
        "id": 376,
        "c": 1
    },
    {
        "name": "이상직",
        "cname": "",
        "party": "",
        "id": 513,
        "c": 1
    },
    {
        "name": "유인태",
        "cname": "",
        "party": "",
        "id": 380,
        "c": 1
    },
    {
        "name": "이미경",
        "cname": "",
        "party": "",
        "id": 517,
        "c": 1
    },
    {
        "name": "김춘진",
        "cname": "",
        "party": "",
        "id": 474,
        "c": 1
    }
]