[{"name_kr":"권성동","name_cn":"權性東","party":"새누리당","district":"강원 강릉시","id":11},{"name_kr":"김영우","name_cn":"金榮宇","party":"새누리당","district":"경기 포천시연천군","id":38},{"name_kr":"박성호","name_cn":"朴成浩","party":"새누리당","district":"경남 창원시의창구","id":102},{"name_kr":"박윤옥","name_cn":"朴允玉","party":"새누리당","district":"비례대표","id":107},{"name_kr":"양창영","name_cn":"楊昶榮","party":"새누리당","district":"비례대표","id":151},{"name_kr":"이노근","name_cn":"李老根","party":"새누리당","district":"서울 노원구갑","id":185},{"name_kr":"정문헌","name_cn":"鄭文憲","party":"새누리당","district":"강원 속초시고성군양양군","id":242},{"name_kr":"정희수","name_cn":"鄭熙秀","party":"새누리당","district":"경북 영천시","id":254},{"name_kr":"홍철호","name_cn":"洪哲鎬","party":"새누리당","district":"경기 김포시","id":289},{"name_kr":"황진하","name_cn":"黃震夏","party":"새누리당","district":"경기 파주시을","id":294}]