[{"id":6030,"link_id":"PRC_B1J3H0V3D1E1W1V6G2Y7V2G7Z3D4D4","title":"장애인의 권리에 관한 협약 유보조항 비준동의안 제출 촉구 결의안","proposed_date":"2013-03-11","decision_date":"2013-04-29","status":"처리","status_detail":"의결","actor_count":13},{"id":3234,"link_id":"PRC_H1M2M0N8P2D9C1E0O5U6Q3G3N0N7F7","title":"지방세특례제한법 일부개정법률안","proposed_date":"2012-08-29","decision_date":"2013-01-01","status":"처리","status_detail":"대안반영폐기","actor_count":18},{"id":10766,"link_id":"PRC_T1R2M0Z7I0R9G1I0Z2P1P3A6U3E2E6","title":"국민건강보험법 일부개정법률안","proposed_date":"2012-07-09","decision_date":"2013-05-07","status":"처리","status_detail":"대안반영폐기","actor_count":14},{"id":14099,"link_id":"PRC_I1G2T0A6U2B5J1I6Q1I2M4U9G4K3F5","title":"산업재해보상보험법 일부개정법률안","proposed_date":"2012-06-25","decision_date":"2012-11-22","status":"처리","status_detail":"대안반영폐기","actor_count":13}]