[{"name_kr":"강석훈","name_cn":"姜錫勳","party":"새누리당","district":null,"id":379},{"name_kr":"김성태","name_cn":"金聖泰","party":"새누리당","district":"서울 강서구을","id":32},{"name_kr":"김용태","name_cn":"金容兌","party":"새누리당","district":"서울 양천구을","id":41},{"name_kr":"김재경","name_cn":"金在庚","party":"새누리당","district":"경남 진주시을","id":46},{"name_kr":"김정훈","name_cn":"金正薰","party":"새누리당","district":"부산 남구갑","id":49},{"name_kr":"김태흠","name_cn":"金泰欽","party":"새누리당","district":"충남 보령시서천군","id":60},{"name_kr":"김학용","name_cn":"金學容","party":"새누리당","district":"경기 안성시","id":61},{"name_kr":"박성호","name_cn":"朴成浩","party":"새누리당","district":"경남 창원시의창구","id":99},{"name_kr":"신동우","name_cn":"申東雨","party":"새누리당","district":"서울 강동구갑","id":130},{"name_kr":"심재철","name_cn":"沈在哲","party":"새누리당","district":"경기 안양시동안구을","id":140},{"name_kr":"안효대","name_cn":"安孝大","party":"새누리당","district":"울산 동구","id":146},{"name_kr":"오신환","name_cn":"吳晨煥","party":"새누리당","district":"서울 관악구을","id":151},{"name_kr":"유의동","name_cn":"兪義東","party":"새누리당","district":"경기 평택시을","id":167},{"name_kr":"윤명희","name_cn":"尹明熙","party":"새누리당","district":"비례대표","id":172},{"name_kr":"이군현","name_cn":"李君賢","party":"새누리당","district":"경남 통영시고성군","id":181},{"name_kr":"이운룡","name_cn":"李雲龍","party":"새누리당","district":"비례대표","id":197},{"name_kr":"한기호","name_cn":"韓起鎬","party":"새누리당","district":"강원 철원군화천군양구군인제군","id":275}]