[{"name_kr":"김동철","name_cn":"金東喆","party":"새정치민주연합","district":null,"id":393},{"name_kr":"김성곤","name_cn":"金星坤","party":"새정치민주연합","district":null,"id":327},{"name_kr":"김승남","name_cn":"金承南","party":"새정치민주연합","district":null,"id":294},{"name_kr":"박혜자","name_cn":"朴惠子","party":"새정치민주연합","district":null,"id":401},{"name_kr":"배기운","name_cn":"裵奇雲","party":"새정치민주연합","district":null,"id":345},{"name_kr":"신학용","name_cn":"辛鶴用","party":"새정치민주연합","district":null,"id":430},{"name_kr":"윤후덕","name_cn":"尹厚德","party":"새정치민주연합","district":null,"id":336},{"name_kr":"이미경","name_cn":"李美卿","party":"새정치민주연합","district":null,"id":349},{"name_kr":"이상민","name_cn":"李相珉","party":"새정치민주연합","district":null,"id":382},{"name_kr":"장하나","name_cn":"張하나","party":"새정치민주연합","district":null,"id":311},{"name_kr":"전병헌","name_cn":"田炳憲","party":"새정치민주연합","district":null,"id":301},{"name_kr":"전정희","name_cn":"全正姬","party":"새정치민주연합","district":null,"id":350},{"name_kr":"정성호","name_cn":"鄭成湖","party":"새정치민주연합","district":null,"id":312}]