[{"id":5420,"link_id":"PRC_L1Y5I0S7Z2K2T1J0E5Y3O4Y6E0M8Q5","bill_id":"1916172","title":"민방위기본법 일부개정법률안","proposed_date":"2015-07-22","decision_date":"0000-00-00","status":"계류","status_detail":"위원회 심사","actor_count":12},{"id":8351,"link_id":"PRC_M1J5G0C6C2A2R1C5A5L9A2I1O7D2Q5","bill_id":"1915698","title":"통계법 일부개정법률안","proposed_date":"2015-06-22","decision_date":"2015-12-31","status":"처리","status_detail":"대안반영폐기","actor_count":10},{"id":9713,"link_id":"PRC_B1C5D0D6Z0Y5K1M8E1Z2J5Q7P9F0J5","bill_id":"1915462","title":"국세기본법 일부개정법률안","proposed_date":"2015-06-05","decision_date":"0000-00-00","status":"계류","status_detail":"위원회 심사","actor_count":10},{"id":11347,"link_id":"PRC_S1W4R1H0I1U3K1Y0C3V4L2H4Z8Y5X3","bill_id":"1912030","title":"사회적경제기본법안","proposed_date":"2014-10-13","decision_date":"0000-00-00","status":"계류","status_detail":"위원회 심사","actor_count":65},{"id":12760,"link_id":"PRC_X1V4M1D0S1J3L1B0H4N0S4L8N0E5T3","bill_id":"1912031","title":"국가재정법 일부개정법률안","proposed_date":"2014-10-13","decision_date":"0000-00-00","status":"계류","status_detail":"위원회 심사","actor_count":65},{"id":11590,"link_id":"PRC_S1T4W0W3Q2U4G1A4P1N5M2P2I9R8Z2","bill_id":"1909850","title":"환경미화원법안","proposed_date":"2014-03-24","decision_date":"0000-00-00","status":"계류","status_detail":"위원회 심사","actor_count":52},{"id":8083,"link_id":"PRC_T1O4P0L3K0G3C1K4Q1B6L5P8W6U4Z5","bill_id":"1909593","title":"우편법 일부개정법률안","proposed_date":"2014-03-03","decision_date":"2014-12-29","status":"처리","status_detail":"공포","actor_count":10},{"id":13081,"link_id":"PRC_M1A3P1F2P1X9X1V8J2B3C3Y7A7H7U4","bill_id":"1908665","title":"사회적경제 기업을 위한 구매촉진 및 판로지원에 관한 특별법안","proposed_date":"2013-12-19","decision_date":"0000-00-00","status":"계류","status_detail":"위원회 심사","actor_count":30},{"id":2372,"link_id":"PRC_N1O3B1W1V2W8T1K7W4T1G0L6L8A3K3","bill_id":"1908178","title":"공탁법 일부개정법률안","proposed_date":"2013-11-28","decision_date":"0000-00-00","status":"계류","status_detail":"위원회 심사","actor_count":10},{"id":14405,"link_id":"PRC_O1P3P1W1Z2X8L1E7J2O8T2E9O1I6F6","bill_id":"1908175","title":"복권 및 복권기금법 일부개정법률안","proposed_date":"2013-11-28","decision_date":"0000-00-00","status":"계류","status_detail":"위원회 심사","actor_count":10},{"id":13072,"link_id":"PRC_I1B3Q1V1X2M8E1N7P4M4X5D8K7A7A5","bill_id":"1908180","title":"국가재정법 일부개정법률안","proposed_date":"2013-11-28","decision_date":"0000-00-00","status":"계류","status_detail":"위원회 심사","actor_count":10},{"id":4421,"link_id":"PRC_A1W3J1B1P2Z7B1Q8Q3O3M2C9O8A1P2","bill_id":"1908146","title":"환경범죄 등의 단속 및 가중처벌에 관한 법률 일부개정법률안","proposed_date":"2013-11-27","decision_date":"2015-01-12","status":"처리","status_detail":"공포","actor_count":10},{"id":13264,"link_id":"PRC_M1O3E1G1N2B7S1Z3H5X8L5P1H9S6O7","bill_id":"1908102","title":"수도권 대기환경개선에 관한 특별법 일부개정법률안","proposed_date":"2013-11-27","decision_date":"0000-00-00","status":"계류","status_detail":"위원회 심사","actor_count":10},{"id":14895,"link_id":"PRC_I1S3I1T1G2D7T1M8J0M9M0U1X9A1E0","bill_id":"1908137","title":"한강수계 상수원수질개선 및 주민지원 등에 관한 법률 일부개정법률안","proposed_date":"2013-11-27","decision_date":"2015-01-12","status":"처리","status_detail":"대안반영폐기","actor_count":10},{"id":6231,"link_id":"PRC_K1V3B1T1T2X7O1G6U4F8G4F1Y0R5I0","bill_id":"1908126","title":"소음·진동관리법 일부개정법률안","proposed_date":"2013-11-27","decision_date":"2013-12-19","status":"처리","status_detail":"철회","actor_count":10},{"id":18231,"link_id":"PRC_T1F3O1H1P2W7X1Y6J1K8G1P0A9G8J9","bill_id":"1908114","title":"생물다양성 보전 및 이용에 관한 법률 일부개정법률안","proposed_date":"2013-11-27","decision_date":"2013-12-19","status":"처리","status_detail":"철회","actor_count":10},{"id":8756,"link_id":"PRC_S1S3V1U1N2K7U1V6J3C6F5Z7U7S9Q9","bill_id":"1908120","title":"자연환경보전법 일부개정법률안","proposed_date":"2013-11-27","decision_date":"2015-01-12","status":"처리","status_detail":"공포","actor_count":10},{"id":11538,"link_id":"PRC_I1F3H1X1F2H7Y1J3Y4D2F2V0Q2B1I9","bill_id":"1908097","title":"국가기술자격법 일부개정법률안","proposed_date":"2013-11-27","decision_date":"2014-04-29","status":"처리","status_detail":"대안반영폐기","actor_count":10},{"id":2984,"link_id":"PRC_F1H3V1I1H2Y7X1R6M4B0J1G9Y2F8B1","bill_id":"1908122","title":"독도 등 도서지역의 생태계 보전에 관한 특별법 일부개정법률안","proposed_date":"2013-11-27","decision_date":"2013-12-19","status":"처리","status_detail":"철회","actor_count":10},{"id":12975,"link_id":"PRC_A1Y3P1K1X2Y7P1R8B1P2Z5I4J4Q0V0","bill_id":"1908140","title":"영산강·섬진강수계 물관리 및 주민지원 등에 관한 법률 일부개정법률안","proposed_date":"2013-11-27","decision_date":"2014-02-28","status":"처리","status_detail":"공포","actor_count":10},{"id":14442,"link_id":"PRC_H1N3P1N1T2O7M1I4U2E0I3A0K4T1K4","bill_id":"1908104","title":"기상법 일부개정법률안","proposed_date":"2013-11-27","decision_date":"2014-02-28","status":"처리","status_detail":"공포","actor_count":10},{"id":5145,"link_id":"PRC_Q1T3U1Y1R2T7L1T3C4O3D0Q0C2S1C3","bill_id":"1908098","title":"석면안전관리법 일부개정법률안","proposed_date":"2013-11-27","decision_date":"2014-02-28","status":"처리","status_detail":"공포","actor_count":10},{"id":7751,"link_id":"PRC_N1K3R1O1F2I7N1A8O1E2X3Y4S1I9K9","bill_id":"1908139","title":"금강수계 물관리 및 주민지원 등에 관한 법률 일부개정법률안","proposed_date":"2013-11-27","decision_date":"2013-12-19","status":"처리","status_detail":"철회","actor_count":10},{"id":12264,"link_id":"PRC_R1H3O1C1C2K7G1B8O0K7G5R3X9Z8I0","bill_id":"1908136","title":"건설폐기물의 재활용촉진에 관한 법률 일부개정법률안","proposed_date":"2013-11-27","decision_date":"2013-12-19","status":"처리","status_detail":"철회","actor_count":10},{"id":3527,"link_id":"PRC_P1T3N1Q1Z2P7P1W3H5W3Y0U9G9P6N9","bill_id":"1908101","title":"야생생물 보호 및 관리에 관한 법률 일부개정법률안","proposed_date":"2013-11-27","decision_date":"2014-02-28","status":"처리","status_detail":"대안반영폐기","actor_count":10},{"id":13118,"link_id":"PRC_Y1N3E1K1L2G7E1Y6Q1S6U5S5F7U8X3","bill_id":"1908113","title":"국립생태원의 설립 및 운영에 관한 법률 일부개정법률안","proposed_date":"2013-11-27","decision_date":"2013-12-19","status":"처리","status_detail":"철회","actor_count":10},{"id":14652,"link_id":"PRC_G1F3I1Z1Z2S7Y1L4D1Y5G2K4V7X1O4","bill_id":"1908103","title":"남녀고용평등과 일·가정 양립 지원에 관한 법률 일부개정법률안","proposed_date":"2013-11-27","decision_date":"0000-00-00","status":"계류","status_detail":"위원회 심사","actor_count":10},{"id":12935,"link_id":"PRC_T1L3A1D1D2Q7T1S6F2F2I3L5G4E2W3","bill_id":"1908116","title":"악취방지법 일부개정법률안","proposed_date":"2013-11-27","decision_date":"2013-12-19","status":"처리","status_detail":"철회","actor_count":10},{"id":6900,"link_id":"PRC_C1G3Y1W1Q2O7V1T8H3X1A2V2L0M8L8","bill_id":"1908143","title":"가축분뇨의 관리 및 이용에 관한 법률 일부개정법률안","proposed_date":"2013-11-27","decision_date":"2013-12-19","status":"처리","status_detail":"철회","actor_count":10},{"id":18883,"link_id":"PRC_J1M3T1G1U2K7T1U8G1Y1N4D1Z3J2C7","bill_id":"1908138","title":"폐기물관리법 일부개정법률안","proposed_date":"2013-11-27","decision_date":"2013-12-26","status":"처리","status_detail":"대안반영폐기","actor_count":10},{"id":8930,"link_id":"PRC_W1C3R1J1U2B7Q1U8W2H6P1C3P2X4N6","bill_id":"1908142","title":"낙동강수계 물관리 및 주민지원 등에 관한 법률 일부개정법률안","proposed_date":"2013-11-27","decision_date":"2013-12-19","status":"처리","status_detail":"철회","actor_count":10},{"id":12187,"link_id":"PRC_K1N3Y1Z1V2J7X1A6R3Y6I4F5Y7A6G6","bill_id":"1908118","title":"수질 및 수생태계 보전에 관한 법률 일부개정법률안","proposed_date":"2013-11-27","decision_date":"2013-12-19","status":"처리","status_detail":"철회","actor_count":10},{"id":14513,"link_id":"PRC_T1G3G1R1R2H7G1Y1Q4Z8N5Q1H3R8R3","bill_id":"1908093","title":"외국인근로자의 고용 등에 관한 법률 일부개정법률안","proposed_date":"2013-11-27","decision_date":"2013-12-31","status":"처리","status_detail":"대안반영폐기","actor_count":10},{"id":17880,"link_id":"PRC_Y1L3F1N1I2P7T1K3N4J1S1Q2Z2C4E4","bill_id":"1908096","title":"근로복지기본법 일부개정법률안","proposed_date":"2013-11-27","decision_date":"2014-04-29","status":"처리","status_detail":"공포","actor_count":10},{"id":4826,"link_id":"PRC_D1K3X1X1E2T7L1K6J1G9Z1T7O2N7D0","bill_id":"1908115","title":"한국환경공단법 일부개정법률안","proposed_date":"2013-11-27","decision_date":"2014-02-28","status":"처리","status_detail":"공포","actor_count":10},{"id":16080,"link_id":"PRC_A1M3U1H1G2V7O1A8W3T1B5T8Y0V6W4","bill_id":"1908144","title":"수도법 일부개정법률안","proposed_date":"2013-11-27","decision_date":"2014-02-28","status":"처리","status_detail":"대안반영폐기","actor_count":10},{"id":6843,"link_id":"PRC_Z1T3C1V1C2M7N1E3T4M4D4C6B3M5Y0","bill_id":"1908100","title":"건설근로자의 고용개선 등에 관한 법률 일부개정법률안","proposed_date":"2013-11-27","decision_date":"0000-00-00","status":"계류","status_detail":"위원회 심사","actor_count":10},{"id":18324,"link_id":"PRC_Q1J3X1C1L2B7H1H6I3A5J3F5A9C6G1","bill_id":"1908117","title":"석면피해구제법 일부개정법률안","proposed_date":"2013-11-27","decision_date":"2013-12-19","status":"처리","status_detail":"철회","actor_count":10},{"id":8866,"link_id":"PRC_E1T3Z1N1A2U7E1M1Z4V7B3P9B6I6L1","bill_id":"1908091","title":"산업안전보건법 일부개정법률안","proposed_date":"2013-11-27","decision_date":"0000-00-00","status":"계류","status_detail":"위원회 심사","actor_count":10},{"id":3116,"link_id":"PRC_J1J3E1M1I2A7O1I4Z2E6E0L8L0K0W0","bill_id":"1908105","title":"대기환경보전법 일부개정법률안","proposed_date":"2013-11-27","decision_date":"2013-12-19","status":"처리","status_detail":"철회","actor_count":10},{"id":19483,"link_id":"PRC_R1H3A1I1I2H7I1F8K2G4G3V2C6V3E4","bill_id":"1908141","title":"잔류성유기오염물질 관리법 일부개정법률안","proposed_date":"2013-11-27","decision_date":"2014-02-28","status":"처리","status_detail":"공포","actor_count":10},{"id":10822,"link_id":"PRC_I1D3F1P1C2D7N1X8F3F2O3E4K5S1W2","bill_id":"1908145","title":"하수도법 일부개정법률안","proposed_date":"2013-11-27","decision_date":"2014-02-28","status":"처리","status_detail":"공포","actor_count":10},{"id":6012,"link_id":"PRC_H1Q3M1C1E0S8K1D7W1H7S1F3I4T8M8","bill_id":"1907675","title":"인문학 진흥 및 인문강좌등의 지원에 관한 법률안","proposed_date":"2013-11-08","decision_date":"2015-12-31","status":"처리","status_detail":"대안반영폐기","actor_count":31},{"id":17970,"link_id":"PRC_R1V3W0O9G1O2T1Q6Q3X9U2A7M1V9O5","bill_id":"1906809","title":"근로자직업능력 개발법 일부개정법률안","proposed_date":"2013-09-12","decision_date":"2014-04-29","status":"처리","status_detail":"공포","actor_count":20},{"id":348,"link_id":"PRC_C1E3C0E8S0V2E1M4F0G5U0R5Q0R5Y2","bill_id":"1906253","title":"법령정보 표시 촉진에 관한 법률안","proposed_date":"2013-08-02","decision_date":"0000-00-00","status":"계류","status_detail":"위원회 심사","actor_count":18},{"id":17119,"link_id":"PRC_O1O3D0J8M0M2K1J4P0K7Q4W9C8D2Q2","bill_id":"1906255","title":"행정절차법 일부개정법률안","proposed_date":"2013-08-02","decision_date":"0000-00-00","status":"계류","status_detail":"위원회 심사","actor_count":18},{"id":10949,"link_id":"PRC_F1H3W0I8F0P2N1D4Q0F6T4F1L1M9R2","bill_id":"1906254","title":"정부조직법 일부개정법률안","proposed_date":"2013-08-02","decision_date":"0000-00-00","status":"계류","status_detail":"위원회 심사","actor_count":18},{"id":7787,"link_id":"PRC_M1O3R0F3K1B8R1L3S5M1O5X6D4N2B1","bill_id":"1904109","title":"초·중등교육법 일부개정법률안","proposed_date":"2013-03-18","decision_date":"2013-12-10","status":"처리","status_detail":"대안반영폐기","actor_count":12},{"id":12529,"link_id":"PRC_M1V3N0D1R1T6T1N7R3L4M2M5Y3K5M5","bill_id":"1903341","title":"국회법 일부개정법률안","proposed_date":"2013-01-16","decision_date":"0000-00-00","status":"계류","status_detail":"위원회 심사","actor_count":20},{"id":1557,"link_id":"PRC_P1B3K0Y1B1K6J1S7H4V0Q5Z6I6I8Y5","bill_id":"1903342","title":"입법교육원법안","proposed_date":"2013-01-16","decision_date":"0000-00-00","status":"계류","status_detail":"위원회 심사","actor_count":20},{"id":4991,"link_id":"PRC_L1I2N1D2B1R3Q1F7L2Q5T2V0V2T0J1","bill_id":"1903086","title":"산업재해보상보험법 일부개정법률안","proposed_date":"2012-12-13","decision_date":"0000-00-00","status":"계류","status_detail":"위원회 심사","actor_count":10},{"id":19184,"link_id":"PRC_I1B2C1P1B0P2T1Q7K2S6D1P6S2D2W2","bill_id":"1902404","title":"공사중단 장기방치 건축물의 정비 등에 관한 특별조치법안","proposed_date":"2012-11-02","decision_date":"2013-04-29","status":"처리","status_detail":"공포","actor_count":22},{"id":3382,"link_id":"PRC_F1H2P1X0P1J1M1R7K1G5L2T4U7G2K0","bill_id":"1902193","title":"공인중개사의 업무 및 부동산 거래신고에 관한 법률 일부개정법률안","proposed_date":"2012-10-11","decision_date":"0000-00-00","status":"계류","status_detail":"위원회 심사","actor_count":13},{"id":17166,"link_id":"PRC_I1P2E1T0S1C1G1Y7Q1R3Z4I6C8A6Y3","bill_id":"1902192","title":"주택임대차보호법 일부개정법률안","proposed_date":"2012-10-11","decision_date":"0000-00-00","status":"계류","status_detail":"위원회 심사","actor_count":13},{"id":14490,"link_id":"PRC_Q1M2L0Z9Y0M4W1A6P0W4Q4I7S1E6T2","bill_id":"1901543","title":"구직서류 반환 등 채용절차의 공정화에 관한 법률안","proposed_date":"2012-09-04","decision_date":"2013-12-26","status":"처리","status_detail":"공포","actor_count":20},{"id":5886,"link_id":"PRC_S1G2O0T8W2X8C1Q5A0I4I4S0N3J4X9","bill_id":"1901358","title":"각급 법원의 설치와 관할구역에 관한 법률 일부개정법률안","proposed_date":"2012-08-28","decision_date":"2013-01-01","status":"처리","status_detail":"대안반영폐기","actor_count":12},{"id":13358,"link_id":"PRC_I1H2U0R7T0C6K1V2B2Q9M3O0Q1R2M0","bill_id":"1900542","title":"국유재산특례제한법 일부개정법률안","proposed_date":"2012-07-06","decision_date":"2013-06-25","status":"처리","status_detail":"대안반영폐기","actor_count":10},{"id":17005,"link_id":"PRC_T1N2S0Q7J0N5M1L4Q5C9D3H9R4N1V7","bill_id":"1900522","title":"국립대학법인 서울대학교 설립·운영에 관한 법률 일부개정법률안","proposed_date":"2012-07-05","decision_date":"2013-01-01","status":"처리","status_detail":"공포","actor_count":14}]