[{"name_kr":"김우남","name_cn":"金宇南","party":"새정치민주연합","id":44},{"name_kr":"김종태","name_cn":"金鍾泰","party":"새누리당","id":54},{"name_kr":"안덕수","name_cn":"安德壽","party":"새누리당","id":318},{"name_kr":"윤명희","name_cn":"尹明熙","party":"새누리당","id":175},{"name_kr":"이개호","name_cn":"李介昊","party":"새정치민주연합","id":183},{"name_kr":"이종배","name_cn":"李鍾培","party":"새누리당","id":212},{"name_kr":"이현재","name_cn":"李賢在","party":"새누리당","id":227},{"name_kr":"장병완","name_cn":"張秉浣","party":"새정치민주연합","id":231},{"name_kr":"홍문표","name_cn":"洪文杓","party":"새누리당","id":282},{"name_kr":"홍철호","name_cn":"洪哲鎬","party":"새누리당","id":289}]