[{"name_kr":"장윤석","name_cn":"張倫碩","party":"새누리당","id":232,"c":514},{"name_kr":"이한성","name_cn":"李翰成","party":"새누리당","id":224,"c":247},{"name_kr":"이만우","name_cn":"李萬雨","party":"새누리당","id":186,"c":239},{"name_kr":"정희수","name_cn":"鄭熙秀","party":"새누리당","id":254,"c":224},{"name_kr":"윤명희","name_cn":"尹明熙","party":"새누리당","id":175,"c":222},{"name_kr":"경대수","name_cn":"慶大秀","party":"새누리당","id":10,"c":218},{"name_kr":"류지영","name_cn":"柳知영","party":"새누리당","id":311,"c":215},{"name_kr":"홍지만","name_cn":"洪志晩","party":"새누리당","id":288,"c":214},{"name_kr":"이노근","name_cn":"李老根","party":"새누리당","id":185,"c":213},{"name_kr":"박인숙","name_cn":"朴仁淑","party":"새누리당","id":108,"c":212},{"name_kr":"이채익","name_cn":"李埰益","party":"새누리당","id":218,"c":208}]