[{"name_kr":"김성곤","name_cn":"金星坤","party":"새정치민주연합","district":"전남 여수시갑","id":31},{"name_kr":"김세연","name_cn":"金世淵","party":"새누리당","district":"부산 금정구","id":35},{"name_kr":"박성호","name_cn":"朴成浩","party":"새누리당","district":"경남 창원시의창구","id":101},{"name_kr":"신성범","name_cn":"愼聖範","party":"새누리당","district":"경남 산청군함양군거창군","id":135},{"name_kr":"이낙연","name_cn":"李洛淵","party":"새정치민주연합","district":null,"id":297},{"name_kr":"이만우","name_cn":"李萬雨","party":"새누리당","district":"비례대표","id":185},{"name_kr":"정희수","name_cn":"鄭熙秀","party":"새누리당","district":"경북 영천시","id":253},{"name_kr":"주호영","name_cn":"朱豪英","party":"새누리당","district":"대구 수성구을","id":261},{"name_kr":"최민희","name_cn":"崔敏姬","party":"새정치민주연합","district":"비례대표","id":269},{"name_kr":"한선교","name_cn":"韓善敎","party":"새누리당","district":"경기 용인시병","id":277}]