[{"name_kr":"김광진","name_cn":"金光珍","party":"새정치민주연합","district":null,"id":292},{"name_kr":"김성주","name_cn":"金成柱","party":"새정치민주연합","district":null,"id":396},{"name_kr":"남인순","name_cn":"南仁順","party":"새정치민주연합","district":null,"id":387},{"name_kr":"유은혜","name_cn":"兪銀惠","party":"새정치민주연합","district":null,"id":348},{"name_kr":"윤후덕","name_cn":"尹厚德","party":"새정치민주연합","district":null,"id":336},{"name_kr":"이개호","name_cn":"李介昊","party":"새정치민주연합","district":null,"id":337},{"name_kr":"이목희","name_cn":"李穆熙","party":"새정치민주연합","district":null,"id":410},{"name_kr":"이찬열","name_cn":"李燦烈","party":"새정치민주연합","district":null,"id":365},{"name_kr":"전해철","name_cn":"全海澈","party":"새정치민주연합","district":null,"id":413},{"name_kr":"정성호","name_cn":"鄭成湖","party":"새정치민주연합","district":null,"id":311}]