[
    {
        "name": "김을동",
        "cname": "金乙東",
        "party": "새누리당",
        "id": 253
    },
    {
        "name": "도종환",
        "cname": "都鐘煥",
        "party": "새정치민주연합",
        "id": 173
    },
    {
        "name": "박창식",
        "cname": "朴昌植",
        "party": "새누리당",
        "id": 212
    },
    {
        "name": "양승조",
        "cname": "梁承晁",
        "party": "새정치민주연합",
        "id": 148
    },
    {
        "name": "윤진식",
        "cname": "尹鎭植",
        "party": "새누리당",
        "id": 343
    },
    {
        "name": "이노근",
        "cname": "李老根",
        "party": "새누리당",
        "id": 26
    },
    {
        "name": "이명수",
        "cname": "李明洙",
        "party": "새누리당",
        "id": 27
    },
    {
        "name": "이상일",
        "cname": "李相逸",
        "party": "새누리당",
        "id": 280
    },
    {
        "name": "정문헌",
        "cname": "鄭文憲",
        "party": "새누리당",
        "id": 256
    },
    {
        "name": "정우택",
        "cname": "鄭宇澤",
        "party": "새누리당",
        "id": 307
    }
]