[{"id":18139,"link_id":"PRC_V1Q5R1F2P1T7K1Z0L3P1I2P4M8R5E2","bill_id":"1918212","title":"역사교과용도서의 다양성 보장에 관한 특별법안","proposed_date":"2015-12-17","decision_date":"0000-00-00","status":"계류","status_detail":"위원회 심사","actor_count":126},{"id":2031,"link_id":"PRC_W1G5L0U9L0Y7Q1P3A3E4H3U1K7P4N8","bill_id":"1916763","title":"장애인복지법 일부개정법률안","proposed_date":"2015-09-07","decision_date":"0000-00-00","status":"계류","status_detail":"위원회 심사","actor_count":14},{"id":6706,"link_id":"PRC_J1M5T0Z4Y0F2U1F6U0G1W0T9J9S5T2","bill_id":"1914564","title":"사립학교법 일부개정법률안","proposed_date":"2015-04-02","decision_date":"0000-00-00","status":"계류","status_detail":"위원회 심사","actor_count":10},{"id":1827,"link_id":"PRC_C1K5A0V4F0X2B1Q6P0N4V1L7I2K0R4","bill_id":"1914565","title":"국립대학법인 서울대학교 설립·운영에 관한 법률 일부개정법률안","proposed_date":"2015-04-02","decision_date":"0000-00-00","status":"계류","status_detail":"위원회 심사","actor_count":10},{"id":3267,"link_id":"PRC_B1N5F0Z4Q0O2X1R6U0S6V0X1U1W1Y3","bill_id":"1914566","title":"국립대학법인 인천대학교 설립·운영에 관한 법률 일부개정법률안","proposed_date":"2015-04-02","decision_date":"0000-00-00","status":"계류","status_detail":"위원회 심사","actor_count":10},{"id":1384,"link_id":"PRC_P1D5D0Q4N0Y1Q1B4S3B8M2A7S6A3M0","bill_id":"1914519","title":"도서관법 전부개정법률안","proposed_date":"2015-04-01","decision_date":"0000-00-00","status":"계류","status_detail":"위원회 심사","actor_count":37},{"id":8967,"link_id":"PRC_C1S5Z0U3R2B0V1F7Z2G5B1E8P4P0R4","bill_id":"1914392","title":"저작권법 일부개정법률안","proposed_date":"2015-03-20","decision_date":"0000-00-00","status":"계류","status_detail":"위원회 심사","actor_count":11},{"id":16627,"link_id":"PRC_M1G4F1L2H1A6O1I0L3F6Q4Y0L3E9N7","bill_id":"1913085","title":"국가재정법 일부개정법률안","proposed_date":"2014-12-16","decision_date":"0000-00-00","status":"계류","status_detail":"위원회 심사","actor_count":13},{"id":3546,"link_id":"PRC_J1Z4O1I1W2X0A1W6L3I5H2P1X7K5I8","bill_id":"1912590","title":"인쇄문화산업 진흥법 일부개정법률안","proposed_date":"2014-11-20","decision_date":"0000-00-00","status":"계류","status_detail":"위원회 심사","actor_count":14},{"id":18743,"link_id":"PRC_B1J4S0Z8K1H2R1U1Z1I5I1W1P0L5Q0","bill_id":"1911376","title":"사립학교법 일부개정법률안","proposed_date":"2014-08-12","decision_date":"0000-00-00","status":"계류","status_detail":"위원회 심사","actor_count":13},{"id":12260,"link_id":"PRC_R1X4J0F6V0T5C1E1B2B5D3A5Q5T3Y8","bill_id":"1910801","title":"응급의료에 관한 법률 일부개정법률안","proposed_date":"2014-06-05","decision_date":"0000-00-00","status":"계류","status_detail":"위원회 심사","actor_count":16},{"id":3491,"link_id":"PRC_P1Q4E0H6I0O5M1X3N4C0B5I3C3O5D6","bill_id":"1910805","title":"신문 등의 진흥에 관한 법률 일부개정법률안","proposed_date":"2014-06-05","decision_date":"0000-00-00","status":"계류","status_detail":"위원회 심사","actor_count":16},{"id":10474,"link_id":"PRC_K1S4X0C6A0W5K1E3T1Q9Y1X2G3A7Q7","bill_id":"1910804","title":"방송법 일부개정법률안","proposed_date":"2014-06-05","decision_date":"0000-00-00","status":"계류","status_detail":"위원회 심사","actor_count":16},{"id":7631,"link_id":"PRC_D1N4B0K5K0V7E1L1P3U1N0Q8B3L2G9","bill_id":"1910500","title":"사립학교법 일부개정법률안","proposed_date":"2014-05-07","decision_date":"0000-00-00","status":"계류","status_detail":"위원회 심사","actor_count":14},{"id":3531,"link_id":"PRC_T1D3A1B2S1K3W1P5Y2V4W1A2C5U6Q5","bill_id":"1908566","title":"콘텐츠산업 진흥법 일부개정법률안","proposed_date":"2013-12-13","decision_date":"0000-00-00","status":"계류","status_detail":"위원회 심사","actor_count":10},{"id":2098,"link_id":"PRC_H1B3D1T1L0F8M1G5F5B8Z2Q9X8I0P3","bill_id":"1907662","title":"지방교육자치에 관한 법률 일부개정법률안","proposed_date":"2013-11-08","decision_date":"0000-00-00","status":"계류","status_detail":"위원회 심사","actor_count":11},{"id":17417,"link_id":"PRC_Y1Y3P1R1D0K7T1B1Q3X1K1N6D2S4A0","bill_id":"1907620","title":"영화 및 비디오물의 진흥에 관한 법률 일부개정법률안","proposed_date":"2013-11-07","decision_date":"0000-00-00","status":"계류","status_detail":"위원회 심사","actor_count":12},{"id":15318,"link_id":"PRC_R1R3S0Q6D1R0R1Z1S2Q2P3L6K7M3G2","bill_id":"1905379","title":"방송법 일부개정법률안","proposed_date":"2013-06-10","decision_date":"0000-00-00","status":"계류","status_detail":"위원회 심사","actor_count":19},{"id":16804,"link_id":"PRC_I1G3L0V6N1N0E1Z1C3N2T2N2Y0F3R7","bill_id":"1905380","title":"인사청문회법 일부개정법률안","proposed_date":"2013-06-10","decision_date":"0000-00-00","status":"계류","status_detail":"위원회 심사","actor_count":18},{"id":19220,"link_id":"PRC_M1K3D0R5G0V7Q1T6T2B8M3H5Y5V6U3","bill_id":"1904865","title":"소득세법 일부개정법률안","proposed_date":"2013-05-07","decision_date":"0000-00-00","status":"계류","status_detail":"위원회 심사","actor_count":22},{"id":18593,"link_id":"PRC_B1N3K0M5O0Z7P1A8W1O6P0L6Z3T0W6","bill_id":"1904868","title":"법인세법 일부개정법률안","proposed_date":"2013-05-07","decision_date":"0000-00-00","status":"계류","status_detail":"위원회 심사","actor_count":22},{"id":4750,"link_id":"PRC_N1G3H0S5K0I7W1J6M4D3N3L1T7C7J3","bill_id":"1904866","title":"조세특례제한법 일부개정법률안","proposed_date":"2013-05-07","decision_date":"0000-00-00","status":"계류","status_detail":"위원회 심사","actor_count":22}]